rx_utils/__init__.py
rx_utils/_internal/__init__.py
rx_utils/_internal/async_utils.py
rx_utils/_internal/from_iterable_factory.py
rx_utils/_internal/types.py
rx_utils/docs/__init__.py
UtilsRxPY-0.0.8.dist-info/LICENSE
UtilsRxPY-0.0.8.dist-info/METADATA
UtilsRxPY-0.0.8.dist-info/WHEEL
UtilsRxPY-0.0.8.dist-info/top_level.txt
UtilsRxPY-0.0.8.dist-info/RECORD
