Metadata-Version: 2.1
Name: UtilsRxPY
Version: 0.0.8
Summary: This is an awesome project!
Home-page: https://github.com/Carsten-Leue/UtilsRxPY
Author: Dr. Carsten Leue
Author-email: carsten.leue@gmx.net
License: MIT
Keywords: UtilsRxPY
Platform: UNKNOWN
Classifier: Topic :: Software Development :: Libraries :: Python Modules
Classifier: Programming Language :: Python :: 3.6
Classifier: Programming Language :: Python :: 3.7
Classifier: Programming Language :: Python :: 3.8
Classifier: Programming Language :: Python :: 3.9
Classifier: Topic :: Software Development :: Libraries :: Python Modules
Classifier: License :: OSI Approved :: MIT License
Classifier: Typing :: Typed
Requires-Python: >=3.6
Requires-Dist: rx
